{
  "id": "https://schema.management.azure.com/schemas/2017-02-28-preview/Microsoft.TimeSeriesInsights.json#",
  "title": "Microsoft.TimeSeriesInsights",
  "description": "Microsoft TimeSeriesInsights Resource Types",
  "$schema": "http://json-schema.org/draft-04/schema#",
  "resourceDefinitions": {
    "environments": {
      "description": "Microsoft.TimeSeriesInsights/environments",
      "properties": {
        "apiVersion": {
          "enum": [
            "2017-02-28-preview"
          ],
          "type": "string"
        },
        "location": {
          "description": "The location of the resource.",
          "type": "string"
        },
        "name": {
          "description": "The resource name",
          "oneOf": [
            {
              "maxLength": 90,
              "minLength": 1,
              "pattern": "^[-\\w\\._\\(\\)]+$",
              "type": "string"
            },
            {
              "$ref": "https://schema.management.azure.com/schemas/common/definitions.json#/definitions/expression"
            }
          ]
        },
        "properties": {
          "description": "Properties used to create an environment.",
          "oneOf": [
            {
              "$ref": "#/definitions/EnvironmentCreationPropertiesOrEnvironmentResourceProperties"
            },
            {
              "$ref": "https://schema.management.azure.com/schemas/common/definitions.json#/definitions/expression"
            }
          ]
        },
        "resources": {
          "items": {
            "oneOf": [
              {
                "$ref": "#/definitions/environments_accessPolicies_childResource"
              },
              {
                "$ref": "#/definitions/environments_eventSources_childResource"
              },
              {
                "$ref": "#/definitions/environments_referenceDataSets_childResource"
              }
            ]
          },
          "type": "array"
        },
        "sku": {
          "description": "The sku determines the capacity of the environment, the SLA (in queries-per-minute and total capacity), and the billing rate.",
          "oneOf": [
            {
              "$ref": "#/definitions/Sku"
            },
            {
              "$ref": "https://schema.management.azure.com/schemas/common/definitions.json#/definitions/expression"
            }
          ]
        },
        "tags": {
          "description": "Key-value pairs of additional properties for the resource.",
          "oneOf": [
            {
              "additionalProperties": {
                "type": "string"
              },
              "properties": {},
              "type": "object"
            },
            {
              "$ref": "https://schema.management.azure.com/schemas/common/definitions.json#/definitions/expression"
            }
          ]
        },
        "type": {
          "enum": [
            "Microsoft.TimeSeriesInsights/environments"
          ],
          "type": "string"
        }
      },
      "required": [
        "location",
        "name",
        "properties",
        "sku",
        "apiVersion",
        "type"
      ],
      "type": "object"
    },
    "environments_accessPolicies": {
      "description": "Microsoft.TimeSeriesInsights/environments/accessPolicies",
      "properties": {
        "apiVersion": {
          "enum": [
            "2017-02-28-preview"
          ],
          "type": "string"
        },
        "name": {
          "description": "The resource name",
          "oneOf": [
            {
              "maxLength": 90,
              "minLength": 1,
              "pattern": "^[-\\w\\._\\(\\)]+$",
              "type": "string"
            },
            {
              "$ref": "https://schema.management.azure.com/schemas/common/definitions.json#/definitions/expression"
            }
          ]
        },
        "properties": {
          "oneOf": [
            {
              "$ref": "#/definitions/AccessPolicyResourceProperties"
            },
            {
              "$ref": "https://schema.management.azure.com/schemas/common/definitions.json#/definitions/expression"
            }
          ]
        },
        "type": {
          "enum": [
            "Microsoft.TimeSeriesInsights/environments/accessPolicies"
          ],
          "type": "string"
        }
      },
      "required": [
        "name",
        "properties",
        "apiVersion",
        "type"
      ],
      "type": "object"
    },
    "environments_eventSources": {
      "description": "Microsoft.TimeSeriesInsights/environments/eventSources",
      "oneOf": [
        {
          "properties": {
            "kind": {
              "description": "The kind of the event source.",
              "oneOf": [
                {
                  "enum": [
                    "Microsoft.EventHub"
                  ],
                  "type": "string"
                },
                {
                  "$ref": "https://schema.management.azure.com/schemas/common/definitions.json#/definitions/expression"
                }
              ]
            },
            "properties": {
              "description": "Properties of the EventHub event source that are required on create or update requests.",
              "oneOf": [
                {
                  "$ref": "#/definitions/EventHubEventSourceCreationPropertiesOrEventHubEventSourceResourceProperties"
                },
                {
                  "$ref": "https://schema.management.azure.com/schemas/common/definitions.json#/definitions/expression"
                }
              ]
            }
          },
          "required": [
            "kind",
            "properties"
          ],
          "type": "object"
        },
        {
          "properties": {
            "kind": {
              "description": "The kind of the event source.",
              "oneOf": [
                {
                  "enum": [
                    "Microsoft.IoTHub"
                  ],
                  "type": "string"
                },
                {
                  "$ref": "https://schema.management.azure.com/schemas/common/definitions.json#/definitions/expression"
                }
              ]
            },
            "properties": {
              "description": "Properties of the IoTHub event source that are required on create or update requests.",
              "oneOf": [
                {
                  "$ref": "#/definitions/IoTHubEventSourceCreationProperties"
                },
                {
                  "$ref": "https://schema.management.azure.com/schemas/common/definitions.json#/definitions/expression"
                }
              ]
            }
          },
          "required": [
            "kind",
            "properties"
          ],
          "type": "object"
        },
        {
          "properties": {
            "kind": {
              "description": "The kind of the event source.",
              "oneOf": [
                {
                  "enum": [
                    "Microsoft.IotHub"
                  ],
                  "type": "string"
                },
                {
                  "$ref": "https://schema.management.azure.com/schemas/common/definitions.json#/definitions/expression"
                }
              ]
            }
          },
          "required": [
            "kind"
          ],
          "type": "object"
        }
      ],
      "properties": {
        "apiVersion": {
          "enum": [
            "2017-02-28-preview"
          ],
          "type": "string"
        },
        "location": {
          "description": "The location of the resource.",
          "type": "string"
        },
        "name": {
          "description": "The resource name",
          "oneOf": [
            {
              "maxLength": 90,
              "minLength": 1,
              "pattern": "^[-\\w\\._\\(\\)]+$",
              "type": "string"
            },
            {
              "$ref": "https://schema.management.azure.com/schemas/common/definitions.json#/definitions/expression"
            }
          ]
        },
        "tags": {
          "description": "Key-value pairs of additional properties for the resource.",
          "oneOf": [
            {
              "additionalProperties": {
                "type": "string"
              },
              "properties": {},
              "type": "object"
            },
            {
              "$ref": "https://schema.management.azure.com/schemas/common/definitions.json#/definitions/expression"
            }
          ]
        },
        "type": {
          "enum": [
            "Microsoft.TimeSeriesInsights/environments/eventSources"
          ],
          "type": "string"
        }
      },
      "required": [
        "location",
        "name",
        "apiVersion",
        "type"
      ]
    },
    "environments_referenceDataSets": {
      "description": "Microsoft.TimeSeriesInsights/environments/referenceDataSets",
      "properties": {
        "apiVersion": {
          "enum": [
            "2017-02-28-preview"
          ],
          "type": "string"
        },
        "location": {
          "description": "The location of the resource.",
          "type": "string"
        },
        "name": {
          "description": "The resource name",
          "oneOf": [
            {
              "maxLength": 63,
              "minLength": 3,
              "pattern": "^[A-Za-z0-9]",
              "type": "string"
            },
            {
              "$ref": "https://schema.management.azure.com/schemas/common/definitions.json#/definitions/expression"
            }
          ]
        },
        "properties": {
          "description": "Properties used to create a reference data set.",
          "oneOf": [
            {
              "$ref": "#/definitions/ReferenceDataSetCreationPropertiesOrReferenceDataSetResourceProperties"
            },
            {
              "$ref": "https://schema.management.azure.com/schemas/common/definitions.json#/definitions/expression"
            }
          ]
        },
        "tags": {
          "description": "Key-value pairs of additional properties for the resource.",
          "oneOf": [
            {
              "additionalProperties": {
                "type": "string"
              },
              "properties": {},
              "type": "object"
            },
            {
              "$ref": "https://schema.management.azure.com/schemas/common/definitions.json#/definitions/expression"
            }
          ]
        },
        "type": {
          "enum": [
            "Microsoft.TimeSeriesInsights/environments/referenceDataSets"
          ],
          "type": "string"
        }
      },
      "required": [
        "location",
        "name",
        "properties",
        "apiVersion",
        "type"
      ],
      "type": "object"
    }
  },
  "definitions": {
    "AccessPolicyResourceProperties": {
      "properties": {
        "description": {
          "description": "An description of the access policy.",
          "type": "string"
        },
        "principalObjectId": {
          "description": "The objectId of the principal in Azure Active Directory.",
          "type": "string"
        },
        "roles": {
          "description": "The list of roles the principal is assigned on the environment.",
          "oneOf": [
            {
              "items": {
                "enum": [
                  "Reader",
                  "Contributor"
                ],
                "type": "string"
              },
              "type": "array"
            },
            {
              "$ref": "https://schema.management.azure.com/schemas/common/definitions.json#/definitions/expression"
            }
          ]
        }
      },
      "type": "object"
    },
    "CreateOrUpdateTrackedResourcePropertiesTags": {
      "additionalProperties": {
        "type": "string"
      },
      "properties": {},
      "type": "object"
    },
    "EnvironmentCreationPropertiesOrEnvironmentResourceProperties": {
      "properties": {
        "dataRetentionTime": {
          "description": "ISO8601 timespan specifying the minimum number of days the environment's events will be available for query.",
          "type": "string"
        },
        "storageLimitExceededBehavior": {
          "description": "The behavior the Time Series Insights service should take when the environment's capacity has been exceeded. If \"PauseIngress\" is specified, new events will not be read from the event source. If \"PurgeOldData\" is specified, new events will continue to be read and old events will be deleted from the environment. The default behavior is PurgeOldData.",
          "oneOf": [
            {
              "enum": [
                "PurgeOldData",
                "PauseIngress"
              ],
              "type": "string"
            },
            {
              "$ref": "https://schema.management.azure.com/schemas/common/definitions.json#/definitions/expression"
            }
          ]
        }
      },
      "required": [
        "dataRetentionTime"
      ],
      "type": "object"
    },
    "EventHubEventSourceCreateOrUpdateParametersOrEventHubEventSourceResource": {
      "properties": {
        "kind": {
          "description": "The kind of the event source.",
          "oneOf": [
            {
              "enum": [
                "Microsoft.EventHub"
              ],
              "type": "string"
            },
            {
              "$ref": "https://schema.management.azure.com/schemas/common/definitions.json#/definitions/expression"
            }
          ]
        },
        "properties": {
          "description": "Properties of the EventHub event source that are required on create or update requests.",
          "oneOf": [
            {
              "$ref": "#/definitions/EventHubEventSourceCreationPropertiesOrEventHubEventSourceResourceProperties"
            },
            {
              "$ref": "https://schema.management.azure.com/schemas/common/definitions.json#/definitions/expression"
            }
          ]
        }
      },
      "required": [
        "kind",
        "properties"
      ],
      "type": "object"
    },
    "EventHubEventSourceCreationPropertiesOrEventHubEventSourceResourceProperties": {
      "properties": {
        "consumerGroupName": {
          "description": "The name of the event hub's consumer group that holds the partitions from which events will be read.",
          "type": "string"
        },
        "eventHubName": {
          "description": "The name of the event hub.",
          "type": "string"
        },
        "eventSourceResourceId": {
          "description": "The resource id of the event source in Azure Resource Manager.",
          "type": "string"
        },
        "keyName": {
          "description": "The name of the SAS key that grants the Time Series Insights service access to the event hub. The shared access policies for this key must grant 'Listen' permissions to the event hub.",
          "type": "string"
        },
        "serviceBusNamespace": {
          "description": "The name of the service bus that contains the event hub.",
          "type": "string"
        },
        "sharedAccessKey": {
          "description": "The value of the shared access key that grants the Time Series Insights service read access to the event hub. This property is not shown in event source responses.",
          "type": "string"
        },
        "timestampPropertyName": {
          "description": "The event property that will be used as the event source's timestamp. If a value isn't specified for timestampPropertyName, or if null or empty-string is specified, the event creation time will be used.",
          "type": "string"
        }
      },
      "required": [
        "consumerGroupName",
        "eventHubName",
        "eventSourceResourceId",
        "keyName",
        "serviceBusNamespace",
        "sharedAccessKey"
      ],
      "type": "object"
    },
    "IoTHubEventSourceCreateOrUpdateParameters": {
      "properties": {
        "kind": {
          "description": "The kind of the event source.",
          "oneOf": [
            {
              "enum": [
                "Microsoft.IoTHub"
              ],
              "type": "string"
            },
            {
              "$ref": "https://schema.management.azure.com/schemas/common/definitions.json#/definitions/expression"
            }
          ]
        },
        "properties": {
          "description": "Properties of the IoTHub event source that are required on create or update requests.",
          "oneOf": [
            {
              "$ref": "#/definitions/IoTHubEventSourceCreationProperties"
            },
            {
              "$ref": "https://schema.management.azure.com/schemas/common/definitions.json#/definitions/expression"
            }
          ]
        }
      },
      "required": [
        "kind",
        "properties"
      ],
      "type": "object"
    },
    "IoTHubEventSourceCreationProperties": {
      "properties": {
        "consumerGroupName": {
          "description": "The name of the iot hub's consumer group that holds the partitions from which events will be read.",
          "type": "string"
        },
        "eventSourceResourceId": {
          "description": "The resource id of the event source in Azure Resource Manager.",
          "type": "string"
        },
        "iotHubName": {
          "description": "The name of the iot hub.",
          "type": "string"
        },
        "keyName": {
          "description": "The name of the Shared Access Policy key that grants the Time Series Insights service access to the iot hub. This shared access policy key must grant 'service connect' permissions to the iot hub.",
          "type": "string"
        },
        "sharedAccessKey": {
          "description": "The value of the Shared Access Policy key that grants the Time Series Insights service read access to the iot hub. This property is not shown in event source responses.",
          "type": "string"
        },
        "timestampPropertyName": {
          "description": "The event property that will be used as the event source's timestamp. If a value isn't specified for timestampPropertyName, or if null or empty-string is specified, the event creation time will be used.",
          "type": "string"
        }
      },
      "required": [
        "consumerGroupName",
        "eventSourceResourceId",
        "iotHubName",
        "keyName",
        "sharedAccessKey"
      ],
      "type": "object"
    },
    "IoTHubEventSourceResource": {
      "properties": {
        "kind": {
          "description": "The kind of the event source.",
          "oneOf": [
            {
              "enum": [
                "Microsoft.IotHub"
              ],
              "type": "string"
            },
            {
              "$ref": "https://schema.management.azure.com/schemas/common/definitions.json#/definitions/expression"
            }
          ]
        }
      },
      "required": [
        "kind"
      ],
      "type": "object"
    },
    "ReferenceDataSetCreationPropertiesOrReferenceDataSetResourceProperties": {
      "properties": {
        "keyProperties": {
          "description": "The list of key properties for the reference data set.",
          "oneOf": [
            {
              "items": {
                "$ref": "#/definitions/ReferenceDataSetKeyProperty"
              },
              "type": "array"
            },
            {
              "$ref": "https://schema.management.azure.com/schemas/common/definitions.json#/definitions/expression"
            }
          ]
        }
      },
      "required": [
        "keyProperties"
      ],
      "type": "object"
    },
    "ReferenceDataSetKeyProperty": {
      "properties": {
        "name": {
          "description": "The name of the key property.",
          "type": "string"
        },
        "type": {
          "description": "The type of the key property.",
          "oneOf": [
            {
              "enum": [
                "String",
                "Double",
                "Bool",
                "DateTime"
              ],
              "type": "string"
            },
            {
              "$ref": "https://schema.management.azure.com/schemas/common/definitions.json#/definitions/expression"
            }
          ]
        }
      },
      "type": "object"
    },
    "Sku": {
      "properties": {
        "capacity": {
          "description": "The capacity of the sku. This value can be changed to support scale out of environments after they have been created.",
          "oneOf": [
            {
              "maximum": 10,
              "minimum": 1,
              "type": "integer"
            },
            {
              "$ref": "https://schema.management.azure.com/schemas/common/definitions.json#/definitions/expression"
            }
          ]
        },
        "name": {
          "description": "The name of this SKU.",
          "oneOf": [
            {
              "enum": [
                "S1",
                "S2"
              ],
              "type": "string"
            },
            {
              "$ref": "https://schema.management.azure.com/schemas/common/definitions.json#/definitions/expression"
            }
          ]
        }
      },
      "required": [
        "capacity",
        "name"
      ],
      "type": "object"
    },
    "environments_accessPolicies_childResource": {
      "description": "accessPolicies",
      "properties": {
        "apiVersion": {
          "enum": [
            "2017-02-28-preview"
          ],
          "type": "string"
        },
        "name": {
          "description": "The resource name",
          "oneOf": [
            {
              "maxLength": 90,
              "minLength": 1,
              "pattern": "^[-\\w\\._\\(\\)]+$",
              "type": "string"
            },
            {
              "$ref": "https://schema.management.azure.com/schemas/common/definitions.json#/definitions/expression"
            }
          ]
        },
        "properties": {
          "oneOf": [
            {
              "$ref": "#/definitions/AccessPolicyResourceProperties"
            },
            {
              "$ref": "https://schema.management.azure.com/schemas/common/definitions.json#/definitions/expression"
            }
          ]
        },
        "type": {
          "enum": [
            "accessPolicies"
          ],
          "type": "string"
        }
      },
      "required": [
        "name",
        "properties",
        "apiVersion",
        "type"
      ],
      "type": "object"
    },
    "environments_eventSources_childResource": {
      "description": "eventSources",
      "oneOf": [
        {
          "properties": {
            "kind": {
              "description": "The kind of the event source.",
              "oneOf": [
                {
                  "enum": [
                    "Microsoft.EventHub"
                  ],
                  "type": "string"
                },
                {
                  "$ref": "https://schema.management.azure.com/schemas/common/definitions.json#/definitions/expression"
                }
              ]
            },
            "properties": {
              "description": "Properties of the EventHub event source that are required on create or update requests.",
              "oneOf": [
                {
                  "$ref": "#/definitions/EventHubEventSourceCreationPropertiesOrEventHubEventSourceResourceProperties"
                },
                {
                  "$ref": "https://schema.management.azure.com/schemas/common/definitions.json#/definitions/expression"
                }
              ]
            }
          },
          "required": [
            "kind",
            "properties"
          ],
          "type": "object"
        },
        {
          "properties": {
            "kind": {
              "description": "The kind of the event source.",
              "oneOf": [
                {
                  "enum": [
                    "Microsoft.IoTHub"
                  ],
                  "type": "string"
                },
                {
                  "$ref": "https://schema.management.azure.com/schemas/common/definitions.json#/definitions/expression"
                }
              ]
            },
            "properties": {
              "description": "Properties of the IoTHub event source that are required on create or update requests.",
              "oneOf": [
                {
                  "$ref": "#/definitions/IoTHubEventSourceCreationProperties"
                },
                {
                  "$ref": "https://schema.management.azure.com/schemas/common/definitions.json#/definitions/expression"
                }
              ]
            }
          },
          "required": [
            "kind",
            "properties"
          ],
          "type": "object"
        },
        {
          "properties": {
            "kind": {
              "description": "The kind of the event source.",
              "oneOf": [
                {
                  "enum": [
                    "Microsoft.IotHub"
                  ],
                  "type": "string"
                },
                {
                  "$ref": "https://schema.management.azure.com/schemas/common/definitions.json#/definitions/expression"
                }
              ]
            }
          },
          "required": [
            "kind"
          ],
          "type": "object"
        }
      ],
      "properties": {
        "apiVersion": {
          "enum": [
            "2017-02-28-preview"
          ],
          "type": "string"
        },
        "location": {
          "description": "The location of the resource.",
          "type": "string"
        },
        "name": {
          "description": "The resource name",
          "oneOf": [
            {
              "maxLength": 90,
              "minLength": 1,
              "pattern": "^[-\\w\\._\\(\\)]+$",
              "type": "string"
            },
            {
              "$ref": "https://schema.management.azure.com/schemas/common/definitions.json#/definitions/expression"
            }
          ]
        },
        "tags": {
          "description": "Key-value pairs of additional properties for the resource.",
          "oneOf": [
            {
              "additionalProperties": {
                "type": "string"
              },
              "properties": {},
              "type": "object"
            },
            {
              "$ref": "https://schema.management.azure.com/schemas/common/definitions.json#/definitions/expression"
            }
          ]
        },
        "type": {
          "enum": [
            "eventSources"
          ],
          "type": "string"
        }
      },
      "required": [
        "location",
        "name",
        "apiVersion",
        "type"
      ]
    },
    "environments_referenceDataSets_childResource": {
      "description": "referenceDataSets",
      "properties": {
        "apiVersion": {
          "enum": [
            "2017-02-28-preview"
          ],
          "type": "string"
        },
        "location": {
          "description": "The location of the resource.",
          "type": "string"
        },
        "name": {
          "description": "The resource name",
          "oneOf": [
            {
              "maxLength": 63,
              "minLength": 3,
              "pattern": "^[A-Za-z0-9]",
              "type": "string"
            },
            {
              "$ref": "https://schema.management.azure.com/schemas/common/definitions.json#/definitions/expression"
            }
          ]
        },
        "properties": {
          "description": "Properties used to create a reference data set.",
          "oneOf": [
            {
              "$ref": "#/definitions/ReferenceDataSetCreationPropertiesOrReferenceDataSetResourceProperties"
            },
            {
              "$ref": "https://schema.management.azure.com/schemas/common/definitions.json#/definitions/expression"
            }
          ]
        },
        "tags": {
          "description": "Key-value pairs of additional properties for the resource.",
          "oneOf": [
            {
              "additionalProperties": {
                "type": "string"
              },
              "properties": {},
              "type": "object"
            },
            {
              "$ref": "https://schema.management.azure.com/schemas/common/definitions.json#/definitions/expression"
            }
          ]
        },
        "type": {
          "enum": [
            "referenceDataSets"
          ],
          "type": "string"
        }
      },
      "required": [
        "location",
        "name",
        "properties",
        "apiVersion",
        "type"
      ],
      "type": "object"
    }
  }
}